ultrasegmentator/__init__.py
ultrasegmentator/configuration.py
ultrasegmentator/paths.py
ultrasegmentator/python_api.py
ultrasegmentator/batch_running/__init__.py
ultrasegmentator/batch_running/collect_results_custom_Decathlon.py
ultrasegmentator/batch_running/collect_results_custom_Decathlon_2d.py
ultrasegmentator/batch_running/generate_lsf_runs_customDecathlon.py
ultrasegmentator/batch_running/benchmarking/__init__.py
ultrasegmentator/batch_running/benchmarking/generate_benchmarking_commands.py
ultrasegmentator/batch_running/benchmarking/summarize_benchmark_results.py
ultrasegmentator/batch_running/release_trainings/__init__.py
ultrasegmentator/batch_running/release_trainings/nnunetv2_v1/__init__.py
ultrasegmentator/batch_running/release_trainings/nnunetv2_v1/collect_results.py
ultrasegmentator/batch_running/release_trainings/nnunetv2_v1/generate_lsf_commands.py
ultrasegmentator/dataset_conversion/Dataset027_ACDC.py
ultrasegmentator/dataset_conversion/Dataset042_BraTS18.py
ultrasegmentator/dataset_conversion/Dataset043_BraTS19.py
ultrasegmentator/dataset_conversion/Dataset073_Fluo_C3DH_A549_SIM.py
ultrasegmentator/dataset_conversion/Dataset114_MNMs.py
ultrasegmentator/dataset_conversion/Dataset115_EMIDEC.py
ultrasegmentator/dataset_conversion/Dataset120_RoadSegmentation.py
ultrasegmentator/dataset_conversion/Dataset137_BraTS21.py
ultrasegmentator/dataset_conversion/Dataset218_Amos2022_task1.py
ultrasegmentator/dataset_conversion/Dataset219_Amos2022_task2.py
ultrasegmentator/dataset_conversion/Dataset220_KiTS2023.py
ultrasegmentator/dataset_conversion/Dataset221_AutoPETII_2023.py
ultrasegmentator/dataset_conversion/Dataset223_AMOS2022postChallenge.py
ultrasegmentator/dataset_conversion/Dataset988_dummyDataset4.py
ultrasegmentator/dataset_conversion/__init__.py
ultrasegmentator/dataset_conversion/convert_MSD_dataset.py
ultrasegmentator/dataset_conversion/convert_raw_dataset_from_old_nnunet_format.py
ultrasegmentator/dataset_conversion/generate_dataset_json.py
ultrasegmentator-0.2.0.dist-info/METADATA
ultrasegmentator-0.2.0.dist-info/WHEEL
ultrasegmentator-0.2.0.dist-info/entry_points.txt
ultrasegmentator-0.2.0.dist-info/top_level.txt
ultrasegmentator-0.2.0.dist-info/RECORD
