Metadata-Version: 2.4
Name: ultrasegmentator
Version: 0.2.0
Author: weki
Classifier: Programming Language :: Python :: 3.10
Classifier: License :: OSI Approved :: MIT License
Requires-Python: >=3.8
Requires-Dist: torch
Requires-Dist: numpy
Requires-Dist: tqdm
Requires-Dist: acvl-utils
Requires-Dist: batchgenerators
Requires-Dist: nibabel
Requires-Dist: dynamic_network_architectures
Requires-Dist: batchgeneratorsv2
Requires-Dist: matplotlib
Requires-Dist: seaborn
Requires-Dist: blosc2
Dynamic: author
Dynamic: classifier
Dynamic: requires-dist
Dynamic: requires-python
